{
    "annotations": {
        "list": []
    },
    "editable": true,
    "fiscalYearStartMonth": 0,
    "graphTooltip": 0,
    "id": null,
    "links": [],
    "liveNow": false,
    "panels": [
        {
            "datasource": {
                "type": "prometheus",
                "uid": "${DS_PROMETHEUS}"
            },
            "fieldConfig": {
                "defaults": {
                    "color": {
                        "mode": "thresholds"
                    },
                    "mappings": [],
                    "thresholds": {
                        "mode": "absolute",
                        "steps": [
                            {
                                "color": "green",
                                "value": null
                            }
                        ]
                    }
                }
            },
            "gridPos": {
                "h": 8,
                "w": 12,
                "x": 0,
                "y": 0
            },
            "id": 1,
            "options": {
                "colorMode": "value",
                "graphMode": "area",
                "justifyMode": "auto",
                "orientation": "auto",
                "reduceOptions": {
                    "calcs": [
                        "lastNotNull"
                    ],
                    "fields": "",
                    "values": false
                },
                "textMode": "auto"
            },
            "targets": [
                {
                    "datasource": {
                        "type": "prometheus",
                        "uid": "${DS_PROMETHEUS}"
                    },
                    "expr": "sum(housing_prediction_requests_total)",
                    "interval": "",
                    "legendFormat": "",
                    "refId": "A"
                }
            ],
            "title": "Total Prediction Requests",
            "type": "stat"
        },
        {
            "datasource": {
                "type": "prometheus",
                "uid": "${DS_PROMETHEUS}"
            },
            "fieldConfig": {
                "defaults": {
                    "color": {
                        "mode": "palette-classic"
                    },
                    "custom": {
                        "axisLabel": "",
                        "axisPlacement": "auto",
                        "barAlignment": 0,
                        "drawStyle": "line",
                        "fillOpacity": 0,
                        "gradientMode": "none",
                        "hideFrom": {
                            "legend": false,
                            "tooltip": false,
                            "vis": false
                        },
                        "lineInterpolation": "linear",
                        "lineWidth": 1,
                        "pointSize": 5,
                        "scaleDistribution": {
                            "type": "linear"
                        },
                        "showPoints": "auto",
                        "spanNulls": false,
                        "stacking": {
                            "group": "A",
                            "mode": "none"
                        },
                        "thresholdsStyle": {
                            "mode": "off"
                        }
                    },
                    "mappings": [],
                    "thresholds": {
                        "mode": "absolute",
                        "steps": [
                            {
                                "color": "green",
                                "value": null
                            }
                        ]
                    },
                    "unit": "s"
                }
            },
            "gridPos": {
                "h": 8,
                "w": 12,
                "x": 12,
                "y": 0
            },
            "id": 2,
            "options": {
                "legend": {
                    "calcs": [],
                    "displayMode": "list",
                    "placement": "bottom"
                },
                "tooltip": {
                    "mode": "single",
                    "sort": "none"
                }
            },
            "targets": [
                {
                    "datasource": {
                        "type": "prometheus",
                        "uid": "${DS_PROMETHEUS}"
                    },
                    "expr": "histogram_quantile(0.95, sum(rate(housing_prediction_duration_seconds_bucket[5m])) by (le, endpoint))",
                    "interval": "",
                    "legendFormat": "95th percentile - {{endpoint}}",
                    "refId": "A"
                }
            ],
            "title": "Response Time (95th percentile)",
            "type": "timeseries"
        },
        {
            "datasource": {
                "type": "prometheus",
                "uid": "${DS_PROMETHEUS}"
            },
            "fieldConfig": {
                "defaults": {
                    "color": {
                        "mode": "thresholds"
                    },
                    "mappings": [
                        {
                            "options": {
                                "0": {
                                    "color": "red",
                                    "index": 1,
                                    "text": "Not Loaded"
                                },
                                "1": {
                                    "color": "green",
                                    "index": 0,
                                    "text": "Loaded"
                                }
                            },
                            "type": "value"
                        }
                    ],
                    "thresholds": {
                        "mode": "absolute",
                        "steps": [
                            {
                                "color": "green",
                                "value": null
                            }
                        ]
                    }
                }
            },
            "gridPos": {
                "h": 4,
                "w": 6,
                "x": 0,
                "y": 8
            },
            "id": 3,
            "options": {
                "colorMode": "background",
                "graphMode": "area",
                "justifyMode": "auto",
                "orientation": "auto",
                "reduceOptions": {
                    "calcs": [
                        "lastNotNull"
                    ],
                    "fields": "",
                    "values": false
                },
                "textMode": "auto"
            },
            "targets": [
                {
                    "datasource": {
                        "type": "prometheus",
                        "uid": "${DS_PROMETHEUS}"
                    },
                    "expr": "housing_model_loaded",
                    "interval": "",
                    "legendFormat": "",
                    "refId": "A"
                }
            ],
            "title": "Model Status",
            "type": "stat"
        },
        {
            "datasource": {
                "type": "prometheus",
                "uid": "${DS_PROMETHEUS}"
            },
            "fieldConfig": {
                "defaults": {
                    "color": {
                        "mode": "thresholds"
                    },
                    "mappings": [],
                    "thresholds": {
                        "mode": "absolute",
                        "steps": [
                            {
                                "color": "green",
                                "value": null
                            }
                        ]
                    }
                }
            },
            "gridPos": {
                "h": 4,
                "w": 6,
                "x": 6,
                "y": 8
            },
            "id": 4,
            "options": {
                "colorMode": "value",
                "graphMode": "area",
                "justifyMode": "auto",
                "orientation": "auto",
                "reduceOptions": {
                    "calcs": [
                        "lastNotNull"
                    ],
                    "fields": "",
                    "values": false
                },
                "textMode": "auto"
            },
            "targets": [
                {
                    "datasource": {
                        "type": "prometheus",
                        "uid": "${DS_PROMETHEUS}"
                    },
                    "expr": "housing_new_data_points_total",
                    "interval": "",
                    "legendFormat": "",
                    "refId": "A"
                }
            ],
            "title": "New Training Data Points",
            "type": "stat"
        },
        {
            "datasource": {
                "type": "prometheus",
                "uid": "${DS_PROMETHEUS}"
            },
            "fieldConfig": {
                "defaults": {
                    "color": {
                        "mode": "thresholds"
                    },
                    "mappings": [],
                    "thresholds": {
                        "mode": "absolute",
                        "steps": [
                            {
                                "color": "green",
                                "value": null
                            }
                        ]
                    }
                }
            },
            "gridPos": {
                "h": 4,
                "w": 6,
                "x": 12,
                "y": 8
            },
            "id": 5,
            "options": {
                "colorMode": "value",
                "graphMode": "area",
                "justifyMode": "auto",
                "orientation": "auto",
                "reduceOptions": {
                    "calcs": [
                        "lastNotNull"
                    ],
                    "fields": "",
                    "values": false
                },
                "textMode": "auto"
            },
            "targets": [
                {
                    "datasource": {
                        "type": "prometheus",
                        "uid": "${DS_PROMETHEUS}"
                    },
                    "expr": "housing_retraining_triggered_total",
                    "interval": "",
                    "legendFormat": "",
                    "refId": "A"
                }
            ],
            "title": "Model Retraining Events",
            "type": "stat"
        }
    ],
    "refresh": "30s",
    "schemaVersion": 36,
    "style": "dark",
    "tags": [
        "california-housing",
        "mlops"
    ],
    "templating": {
        "list": []
    },
    "time": {
        "from": "now-1h",
        "to": "now"
    },
    "timepicker": {},
    "timezone": "",
    "title": "California Housing API - Basic Monitoring",
    "uid": "housing_api_basic",
    "version": 1,
    "weekStart": ""
}